Topsis-Tanvir-102303389/__init__.py
topsis/__init__.py
topsis/topsis.py
topsis_tanvir_102303389-1.0.dist-info/METADATA
topsis_tanvir_102303389-1.0.dist-info/WHEEL
topsis_tanvir_102303389-1.0.dist-info/top_level.txt
topsis_tanvir_102303389-1.0.dist-info/RECORD
