Metadata-Version: 2.1
Name: topsis-tanvir-102303389
Version: 1.0
Summary: TOPSIS implementation as a Python package
Author: Tanvir
Author-email: tanvir102303389@gmail.com
Requires-Dist: pandas
Requires-Dist: numpy
